gcp_utilities/__init__.py
gcp_utilities/main.py
gcp_utilities-0.0.1.dist-info/licenses/LICENSE
gcp_utilities-0.0.1.dist-info/WHEEL
gcp_utilities-0.0.1.dist-info/METADATA
gcp_utilities-0.0.1.dist-info/RECORD
