Metadata-Version: 2.4
Name: gcp_utilities
Version: 0.0.1
Summary: Simple utilities for GCP BigQuery, Cloud Storage and Cloud Logging
Author: Collins Mmasaba
Author-email: Collins Mmasaba <mmasabacollins9@gmail.com>
License-Expression: MIT
License-File: LICENSE
Classifier: Programming Language :: Python :: 3
Classifier: Operating System :: OS Independent
Requires-Python: >=3.12
Project-URL: Homepage, https://github.com/cmmasaba/gcp-tools
Project-URL: Issues, https://github.com/cmmasaba/gcp-tools/issues
